pdf4md/__init__.py
pdf4md/main.py
pdf4md-0.0.1.dist-info/entry_points.txt
pdf4md-0.0.1.dist-info/LICENSE
pdf4md-0.0.1.dist-info/METADATA
pdf4md-0.0.1.dist-info/WHEEL
pdf4md-0.0.1.dist-info/RECORD
